{
 	"subheader": "Must See",

	"stripenav-items": [

	],

	"promo-items": [
		{
			"classes": "double-spacing--vertical@s spacing--vertical@m spacing--vertical@l gel-1/1@xs gel-1/1@m gel-2/4@l gel-2/5@xxl at-line-b-until@s",
			"promo": {
				"classes": "promo--lead promo--has-media promo--has-image-4by3 label--breaking icon--large ",
				"image": "",
        "background-image": "https://ichef.bbci.co.uk/images/ic/720x405/p04p5lb7.jpg",
				"headline": "Canadian mayor's turban fitting goes viral",
				"summary": "",
				"url": "http://www.test.bbc.com/news/av/world-us-canada-38573561",
				"label-text": "",
				"media-duration": "",
				"icon": "video",
				"metadata": {
					"timestamp": "",
					"live-status": "",
					"section": "",
          "url": "http://www.bbc.com/news/world/us_and_canada",
					"comments": ""
				}
			}
		},
    {
      "classes": "spacing--vertical@s spacing--vertical@m spacing--vertical@l spacing--vertical@xxl gel-1/1@xs gel-1/3@m gel-1/4@l gel-1/5@xxl at-line-b-until@s",
      "on_now_heading": "On Now",
      "on_now": [
        {
        "promo": {
          "on_now_heading": "How to Watch",
          "on_now_channel": "BBC World News TV",
          "url": "http://www.bbc.co.uk/news/world_radio_and_tv",
          "on_now_summary": "",
          "classes": "",
        "programme-data": "",
        "air_date": "",
        "icon": "tv",
        "live-media": ""
        }
      },
      {
      "promo": {
      "on_now_heading": "Listen live",
      "on_now_channel": "BBC World Service Radio",
      "url": "http://www.bbc.co.uk/radio/player/bbc_world_service",
      "on_now_summary": "",
      "programme-data": "",
      "air_date": "",
      "icon": "audio",
      "live-media": ""
      }
    }
    ]
    },
		{
			"classes": "spacing--vertical@s spacing--vertical@m spacing--vertical@l spacing--vertical@xxl gel-1/1@xs gel-1/3@m gel-1/4@l gel-1/5@xxl at-line-b-until@s",
      "promo": {
				"classes": " promo--standard promo--horizontal@xs promo--has-image-16by9 label--breaking icon--small",
				"image": "https://ichef-1.bbci.co.uk/news/660/cpsprodpb/5D34/production/_94706832_money.png",
				"headline": "Moldova art exhibit illustrates $1bn banking fraud",
				"summary": "",
				"url": "http://www.bbc.com/news/blogs-news-from-elsewhere-39004441",
				"label-text": "",
				"media-duration": "1:23",
				"icon": "",
				"metadata": {
					"timestamp": "",
					"live-status": "",
					"section": "",
          "url": "http://www.bbc.com/news/world/europe",
					"comments": ""
				}
			}
		},
		{
			"classes": "spacing--vertical@s spacing--vertical@m spacing--vertical@l spacing--vertical@xxl gel-1/1@xs gel-1/3@m gel-1/4@l gel-1/5@xxl at-line-b-until@s",
      "promo": {
				"classes": " promo--standard promo--horizontal@xs promo--has-image-16by9 label--breaking icon--small",
				"image": "https://ichef-1.bbci.co.uk/news/976/cpsprodpb/9A9B/production/_94697593_hi037836930.jpg",
				"headline": "Week in pictures: News photos from around the world",
				"summary": "",
				"url": "http://www.bbc.com/news/in-pictures-39005579",
				"label-text": "",
				"media-duration": "",
				"icon": "image",
				"metadata": {
					"timestamp": "",
					"live-status": "",
					"section": "",
          "url": "http://www.bbc.com/news/in_pictures",
					"comments": ""
				}
			}
		},
		{
			"classes": "spacing--vertical@s spacing--vertical@m spacing--vertical@l  gel-1/1@xs gel-1/3@m gel-1/4@l gel-1/5@xxl at-line-b-until@s",
      "promo": {
				"classes": " promo--standard promo--horizontal@xs promo--has-image-16by9 label--breaking icon--small",
				"image": "https://ichef.bbci.co.uk/live-experience/cps/624/cpsprodpb/1133D/production/_94816407_mediaitem94816406.jpg",
				"headline": "Inside Iraqi offensive to recapture Mosul airport",
				"summary": "",
				"url": "http://www.test.bbc.com/news/av/world-middle-east-39064599",
				"label-text": "",
				"media-duration": "0:56",
				"icon": "video",
				"metadata": {
					"timestamp": "",
					"live-status": "",
					"section": "",
          "url": "http://www.bbc.com/news/world/us_and_canada",
					"comments": ""
				}
			}
		},
		{
			"classes": "spacing--vertical@s spacing--vertical@m spacing--vertical@l gel-1/1@xs gel-1/3@m gel-1/4@l gel-1/5@xxl at-line-b-until@s",
      "promo": {
				"classes": "promo--standard promo--horizontal@xs promo--has-image-16by9 label--breaking icon--small",
				"image": "https://ichef.bbci.co.uk/live-experience/cps/624/cpsprodpb/983B/production/_94817983_mediaitem94811960.jpg",
				"headline": "Tiger knocks drone from the sky to keep fit",
				"summary": "",
				"url": "http://www.test.bbc.com/news/av/world-asia-39066658",
				"label-text": "",
				"media-duration": "0:28",
				"icon": "video",
				"metadata": {
					"timestamp": "",
					"live-status": "",
					"section": "",
          "url": "http://www.bbc.com/news/world/us_and_canada",
					"comments": ""
				}
			}
		},
		{
			"classes": " spacing--vertical@m spacing--vertical@l gel-1/1@xs gel-1/3@m gel-1/4@l gel-1/5@xxl ",
      "promo": {
				"classes": "promo--standard promo--horizontal@xs promo--has-image-16by9 label--breaking icon--small",
				"image": "https://ichef.bbci.co.uk/news/624/cpsprodpb/197F/production/_94772560_flags.jpg",
				"headline": "Texas lawmaker: 'Don't use Chile flag emoji when you mean Texas!'",
				"summary": "",
				"url": "http://www.bbc.com/news/world-latin-america-39039170",
				"label-text": "",
				"media-duration": "3:43",
				"icon": "",
				"metadata": {
					"timestamp": "",
					"live-status": "",
					"section": "",
          "url": "http://www.bbc.com/news/world/latin_america",
					"comments": ""
				}
			}
		}
	]
}
